downloader_folder/__init__.py
downloader_folder/downloader.py
realDownloader-1.0.1.dist-info/LICENSE
realDownloader-1.0.1.dist-info/METADATA
realDownloader-1.0.1.dist-info/WHEEL
realDownloader-1.0.1.dist-info/entry_points.txt
realDownloader-1.0.1.dist-info/top_level.txt
realDownloader-1.0.1.dist-info/RECORD
