Metadata-Version: 2.1
Name: realDownloader
Version: 1.0.1
Summary: instant way to create a flask api for your databases
Home-page: UNKNOWN
Author: Mehdi YAHIA CHERIF
Author-email: UNKNOWN
License: GPL-3.0
Platform: UNKNOWN
Classifier: License :: OSI Approved :: GNU Affero General Public License v3 or later (AGPLv3+)
Classifier: Programming Language :: Python :: 3
Classifier: Programming Language :: Python :: 3.7
Requires-Dist: certifi (==2020.12.5)
Requires-Dist: chardet (==3.0.4)
Requires-Dist: idna (==2.10)
Requires-Dist: requests (==2.25.0)
Requires-Dist: tqdm (==4.54.1)
Requires-Dist: urllib3 (==1.26.2)
